mkdocs_github/404.html
mkdocs_github/__init__.py
mkdocs_github/base.html
mkdocs_github/content.html
mkdocs_github/main.html
mkdocs_github/mkdocs_theme.yml
mkdocs_github/nav.html
mkdocs_github/search.html
mkdocs_github/css/theme.css
mkdocs_github/js/theme.js
mkdocs_github/search/search.html
mkdocs_github-0.0.6.dist-info/LICENSE
mkdocs_github-0.0.6.dist-info/METADATA
mkdocs_github-0.0.6.dist-info/WHEEL
mkdocs_github-0.0.6.dist-info/entry_points.txt
mkdocs_github-0.0.6.dist-info/top_level.txt
mkdocs_github-0.0.6.dist-info/RECORD
