Metadata-Version: 2.1
Name: mkdocs-github
Version: 0.0.6
Summary: simple theme github for Mkdocs
Home-page: https://github.com/g3xx/mkdocs-Github
Author: g3xx
Author-email: cc@c0de.pro
License: MIT
Platform: UNKNOWN
